__init__.py
simplecolorpalette.py
simple_color_palette-0.1.0.dist-info/licenses/LICENSE
simple_color_palette-0.1.0.dist-info/METADATA
simple_color_palette-0.1.0.dist-info/WHEEL
simple_color_palette-0.1.0.dist-info/top_level.txt
simple_color_palette-0.1.0.dist-info/RECORD
