Metadata-Version: 2.4
Name: simple-color-palette
Version: 0.1.0
Summary: Python package for https://github.com/simple-color-palette/simple-color-palette
Requires-Python: >=3.14
License-File: LICENSE
Requires-Dist: ruff>=0.14.10
Dynamic: license-file
